MANIFEST.in
README.rst
setup.py
crowfood/__init__.py
crowfood/cli.py
crowfood/cluster_regexp.py
crowfood/engine.py
crowfood/graph.py
crowfood/utils.py
crowfood.egg-info/PKG-INFO
crowfood.egg-info/SOURCES.txt
crowfood.egg-info/dependency_links.txt
crowfood.egg-info/entry_points.txt
crowfood.egg-info/requires.txt
crowfood.egg-info/top_level.txt