Metadata-Version: 1.1
Name: crowfood
Version: 0.4.1
Summary: C/C++ dependency graphing using snakefood
Home-page: https://github.com/neothemachine/crowfood
Author: Maik Riechert
Author-email: maik.riechert@arcor.de
License: UNKNOWN
Platform: UNKNOWN
Classifier: Development Status :: 4 - Beta
Classifier: Natural Language :: English
Classifier: License :: OSI Approved :: MIT License
Classifier: Programming Language :: Python :: 2.7
Classifier: Programming Language :: Python :: 3
Classifier: Operating System :: OS Independent
